danube_delta/__init__.py
danube_delta/jinja_filters.py
danube_delta/settings.py
danube_delta/cli/__init__.py
danube_delta/cli/deploy.py
danube_delta/cli/helpers.py
danube_delta/cli/lint.py
danube_delta/cli/photos.py
danube_delta/cli/preview.py
danube_delta/cli/publish.py
danube_delta/cli/update.py
danube_delta/cli/write.py
danube_delta/plugins/__init__.py
danube_delta/plugins/authors.py
danube_delta/plugins/code_blocks.py
danube_delta/plugins/featured_image.py
danube_delta/plugins/headings.py
danube_delta/plugins/media.py
danube_delta/plugins/outdated_article.py
danube_delta/plugins/plain_summary.py
danube_delta/plugins/tables.py
danube_delta/plugins/utils.py
danube_delta/theme/static/css/bootstrap.min.css
danube_delta/theme/static/css/code.css
danube_delta/theme/static/css/font-awesome.min.css
danube_delta/theme/static/css/main.css
danube_delta/theme/static/fonts/FontAwesome.otf
danube_delta/theme/static/fonts/fontawesome-webfont.eot
danube_delta/theme/static/fonts/fontawesome-webfont.svg
danube_delta/theme/static/fonts/fontawesome-webfont.ttf
danube_delta/theme/static/fonts/fontawesome-webfont.woff
danube_delta/theme/static/fonts/fontawesome-webfont.woff2
danube_delta/theme/templates/article.html
danube_delta/theme/templates/base.html
danube_delta/theme/templates/index.html
danube_delta/theme/templates/page.html
danube_delta-2.1.0.dist-info/LICENSE
danube_delta-2.1.0.dist-info/METADATA
danube_delta-2.1.0.dist-info/WHEEL
danube_delta-2.1.0.dist-info/entry_points.txt
danube_delta-2.1.0.dist-info/top_level.txt
danube_delta-2.1.0.dist-info/RECORD
