Metadata-Version: 2.1
Name: danube-delta
Version: 2.1.0
Summary: Honza Javorek's Pelican setup
Home-page: http://github.com/honzajavorek/danube-delta
Author: Honza Javorek
Author-email: mail@honzajavorek.cz
License: MIT
Keywords: pelican blog
Platform: UNKNOWN
Classifier: Environment :: Console
Classifier: Operating System :: OS Independent
Classifier: License :: OSI Approved :: MIT License
Classifier: Programming Language :: Python
Classifier: Programming Language :: Python :: 3
Classifier: Programming Language :: Python :: 3 :: Only
License-File: LICENSE
Requires-Dist: pelican
Requires-Dist: ghp-import
Requires-Dist: lxml
Requires-Dist: pillow
Requires-Dist: python-slugify
Requires-Dist: click
Requires-Dist: markdown
Requires-Dist: colorama
Requires-Dist: requests
Requires-Dist: flake8
Provides-Extra: release
Requires-Dist: python-semantic-release ; extra == 'release'
Provides-Extra: tests
Requires-Dist: pytest-runner ; extra == 'tests'
Requires-Dist: pytest (>=3.6) ; extra == 'tests'
Requires-Dist: pytest-cov ; extra == 'tests'
Requires-Dist: coveralls ; extra == 'tests'
Requires-Dist: flake8 ; extra == 'tests'
